elasticsearch_tocsv/__init__.py
elasticsearch_tocsv/elasticsearch_tocsv.py
elasticsearch_tocsv/helpers/__init__.py
elasticsearch_tocsv/helpers/arguments_checkers.py
elasticsearch_tocsv/helpers/color_wrappers.py
elasticsearch_tocsv/helpers/connection_tools.py
elasticsearch_tocsv/helpers/csv_handlers.py
elasticsearch_tocsv/helpers/interval_builders.py
elasticsearch_tocsv/helpers/utility_functions.py
elasticsearch_tocsv/utils/CustomLogger.py
elasticsearch_tocsv/utils/TqdmLoggingHandler.py
elasticsearch_tocsv/utils/__init__.py
elasticsearch_tocsv-0.1.4.dist-info/LICENSE
elasticsearch_tocsv-0.1.4.dist-info/METADATA
elasticsearch_tocsv-0.1.4.dist-info/WHEEL
elasticsearch_tocsv-0.1.4.dist-info/entry_points.txt
elasticsearch_tocsv-0.1.4.dist-info/top_level.txt
elasticsearch_tocsv-0.1.4.dist-info/RECORD
