Metadata-Version: 2.1
Name: elasticsearch-tocsv
Version: 0.1.4
Summary: Simple python tool to extract massive amounts of documents - raw or aggregated - from Elasticsearch into a csv file exploiting multiprocessing and leveraging the underlying elasticsearch-py package
Home-page: https://github.com/fabiopipitone/elasticsearch-tocsv
Author: Fabio Pipitone
Author-email: fabio.pipitone93@gmail.com
License: GPLv2
Keywords: elasticsearch,export,csv,report,kibana,elasticsearch-py
Platform: UNKNOWN
Classifier: Programming Language :: Python :: 3
Classifier: License :: OSI Approved :: GNU General Public License v2 or later (GPLv2+)
Classifier: Operating System :: OS Independent
Requires-Python: >=3.8, <4
Requires-Dist: requests (>==2.22.0)
Requires-Dist: elasticsearch (>=7.9.1)
Requires-Dist: tqdm (>=4.49.0)
Requires-Dist: pandas (>=1.1.2)
Requires-Dist: pytz (>=2020.1)
